dating/__init__.py
dating/ranges.py
dating-0.0.2.dist-info/DESCRIPTION.rst
dating-0.0.2.dist-info/METADATA
dating-0.0.2.dist-info/RECORD
dating-0.0.2.dist-info/WHEEL
dating-0.0.2.dist-info/metadata.json
dating-0.0.2.dist-info/top_level.txt
