Metadata-Version: 2.0
Name: dating
Version: 0.0.2
Summary: Library for handling date ranges and time periods in a business context (based on Arrow)
Home-page: https://github.com/a115/python-dating
Author: Jordan Dimov
Author-email: jdimov@mlke.net
License: MIT
Keywords: datetime date range ISO8601 arrow
Platform: UNKNOWN
Classifier: Development Status :: 4 - Beta
Classifier: Intended Audience :: Developers
Classifier: Topic :: Software Development
Classifier: License :: OSI Approved :: MIT License
Classifier: Programming Language :: Python :: 3
Classifier: Programming Language :: Python :: 3.6
Requires-Python: >=3
Requires-Dist: arrow (>=0.10.0)
